mkdocs_note/__init__.py
mkdocs_note/cli.py
mkdocs_note/config.py
mkdocs_note/graph.py
mkdocs_note/plugin.py
mkdocs_note/static/graph.css
mkdocs_note/static/graph.js
mkdocs_note/utils/__init__.py
mkdocs_note/utils/meta.py
mkdocs_note/utils/scanner.py
mkdocs_note/utils/cli/__init__.py
mkdocs_note/utils/cli/commands.py
mkdocs_note/utils/cli/common.py
mkdocs_note-3.1.0.dist-info/licenses/LICENSE
mkdocs_note-3.1.0.dist-info/METADATA
mkdocs_note-3.1.0.dist-info/WHEEL
mkdocs_note-3.1.0.dist-info/entry_points.txt
mkdocs_note-3.1.0.dist-info/top_level.txt
mkdocs_note-3.1.0.dist-info/RECORD
