Metadata-Version: 2.4
Name: mkdocs-note
Version: 3.1.0
Summary: A MkDocs plugin to add note boxes to your documentation.
Author-email: virtualguard101 <virtualguard101@gmail.com>
License-Expression: GPL-3.0-or-later
Project-URL: Repository, https://github.com/virtualguard101/mkdocs-note
Project-URL: Homepage, https://blog.virtualguard101.com/mkdocs-note
Project-URL: Issues, https://github.com/virtualguard101/mkdocs-note/issues
Classifier: Programming Language :: Python :: 3
Classifier: Operating System :: OS Independent
Requires-Python: >=3.12
License-File: LICENSE
Requires-Dist: mkdocs>=1.6.1
Requires-Dist: colorlog>=6.9.0
Requires-Dist: pyyaml>=6.0
Requires-Dist: pymdown-extensions>=10.15
Requires-Dist: mkdocs-material>=9.6.4
Requires-Dist: mkdocs-material-extensions>=1.3.1
Requires-Dist: mkdocs-jupyter>=0.25.1
Requires-Dist: mkdocs-minify-plugin>=0.8.0
Requires-Dist: mkdocs-git-revision-date-localized-plugin>=1.4.0
Requires-Dist: mkdocs-awesome-nav>=3.2.0
Requires-Dist: mkdocstrings-python>=1.18.2
Provides-Extra: dev
Requires-Dist: click==8.2.1; extra == "dev"
Requires-Dist: pytest>=8.4.2; extra == "dev"
Requires-Dist: pre-commit>=4.3.0; extra == "dev"
Requires-Dist: ruff>=0.14.1; extra == "dev"
Requires-Dist: pytest-cov; extra == "dev"
Requires-Dist: mkdocs-material>=9.6.4; extra == "dev"
Requires-Dist: mkdocs-minify-plugin>=0.8.0; extra == "dev"
Requires-Dist: mkdocs-git-revision-date-localized-plugin>=1.4.0; extra == "dev"
Requires-Dist: pymdown-extensions>=10.0; extra == "dev"
Provides-Extra: test
Requires-Dist: pytest-cov; extra == "test"
Dynamic: license-file
